TDR/TDR.py
TDR/__init__.py
TopDR-0.4.dist-info/LICENSE
TopDR-0.4.dist-info/METADATA
TopDR-0.4.dist-info/WHEEL
TopDR-0.4.dist-info/top_level.txt
TopDR-0.4.dist-info/RECORD
