Metadata-Version: 2.2
Name: TopDR
Version: 0.4
Summary: Topological Dimension Reduction
Home-page: https://github.com/EvReN-jr/TDR_share
Author: BOYABATLI, Kenan Evren; YİĞT, Uğur
Author-email: kbybtli@gmail.com; ugur.yigit@medeniyet.edu.tr
Classifier: Programming Language :: Python :: 3
Classifier: License :: OSI Approved :: MIT License
Classifier: Operating System :: OS Independent
Requires-Python: >=3.6
License-File: LICENSE
Requires-Dist: pandas>=1.0.0
Requires-Dist: numpy>=1.18.0
Requires-Dist: statistics
Dynamic: author
Dynamic: author-email
Dynamic: classifier
Dynamic: description
Dynamic: description-content-type
Dynamic: home-page
Dynamic: requires-dist
Dynamic: requires-python
Dynamic: summary
